uQCme/__init__.py
uQCme/app/__init__.py
uQCme/app/main.py
uQCme/app/plot.py
uQCme/cli/__init__.py
uQCme/cli/main.py
uQCme/core/__init__.py
uQCme/core/config.py
uQCme/core/engine.py
uQCme/core/exceptions.py
uQCme/core/loader.py
uQCme/core/logging.py
uQCme/core/schemas.py
uQCme/defaults/QC_rules.tsv
uQCme/defaults/QC_tests.tsv
uQCme/defaults/config.yaml
uQCme/defaults/mapping.yaml
uqcme-0.7.0.dist-info/METADATA
uqcme-0.7.0.dist-info/WHEEL
uqcme-0.7.0.dist-info/entry_points.txt
uqcme-0.7.0.dist-info/licenses/LICENSE
uqcme-0.7.0.dist-info/RECORD
