Metadata-Version: 2.4
Name: uQCme
Version: 0.7.0
Summary: Microbial Quality Control Dashboard
Project-URL: Repository, https://github.com/ssi-dk/uQCme
Author-email: Kim Ng <kimn@ssi.dk>
License-Expression: MIT
License-File: LICENSE
Keywords: dashboard,microbial,qc,quality-control,sequencing
Classifier: License :: OSI Approved :: MIT License
Classifier: Operating System :: OS Independent
Classifier: Programming Language :: Python :: 3
Classifier: Programming Language :: Python :: 3.12
Requires-Python: <3.13,>=3.12
Requires-Dist: pandas>=1.5.0
Requires-Dist: pandera>=0.18.0
Requires-Dist: pydantic>=2.0.0
Requires-Dist: pyyaml>=6.0
Provides-Extra: all
Requires-Dist: openpyxl>=3.0.0; extra == 'all'
Requires-Dist: plotly>=5.15.0; extra == 'all'
Requires-Dist: streamlit>=1.28.0; extra == 'all'
Provides-Extra: app
Requires-Dist: openpyxl>=3.0.0; extra == 'app'
Requires-Dist: plotly>=5.15.0; extra == 'app'
Requires-Dist: streamlit>=1.28.0; extra == 'app'
Provides-Extra: cli
